_packagedcode/__init__.py
_packagedcode/models.py
_packagedcode/pypi.py
_packagedcode/pypi.py.ABOUT
_packagedcode/pypi.py.NOTICE
_packagedcode/pypi_setup_py.py
_packagedcode/pypi_setup_py.py.ABOUT
_packagedcode/pypi_setup_py.py.LICENSE
_packagedcode/utils.py
python_inspector/__init__.py
python_inspector/api.py
python_inspector/cli_utils.py
python_inspector/dependencies.py
python_inspector/error.py
python_inspector/lockfile.py
python_inspector/package_data.py
python_inspector/resolution.py
python_inspector/resolution.py.ABOUT
python_inspector/resolution.py.LICENSE
python_inspector/resolve_cli.py
python_inspector/settings.py
python_inspector/setup_py_live_eval.py
python_inspector/setup_py_live_eval.py.ABOUT
python_inspector/setup_py_live_eval.py.LICENSE
python_inspector/utils.py
python_inspector/utils_pip_compatibility_tags.py
python_inspector/utils_pip_compatibility_tags.py.ABOUT
python_inspector/utils_pypi.py
python_inspector/utils_pypi.py.ABOUT
python_inspector/utils_pypi_supported_tags.py
python_inspector/utils_pypi_supported_tags.py.ABOUT
python_inspector-0.15.0.dist-info/licenses/AUTHORS.rst
python_inspector-0.15.0.dist-info/licenses/CHANGELOG.rst
python_inspector-0.15.0.dist-info/licenses/CODE_OF_CONDUCT.rst
python_inspector-0.15.0.dist-info/licenses/NOTICE
python_inspector-0.15.0.dist-info/licenses/README.rst
python_inspector-0.15.0.dist-info/licenses/apache-2.0.LICENSE
python_inspector-0.15.0.dist-info/METADATA
python_inspector-0.15.0.dist-info/WHEEL
python_inspector-0.15.0.dist-info/entry_points.txt
python_inspector-0.15.0.dist-info/top_level.txt
python_inspector-0.15.0.dist-info/RECORD
