Metadata-Version: 2.4
Name: python-inspector
Version: 0.15.0
Summary: python-inspector is is a collection of utilities to collect PyPI package metadata and resolve packages dependencies.
Home-page: https://github.com/aboutcode-org/python-inspector
Author: nexB. Inc. and others
Author-email: info@aboutcode.org
License: Apache-2.0
Keywords: open source,scan,package,dependency,pypi,python,SBOM,sca,dependencies,dependency resolution,resolver,resolvelib,pip,requirements
Classifier: Development Status :: 4 - Beta
Classifier: Intended Audience :: Developers
Classifier: Programming Language :: Python :: 3
Classifier: Programming Language :: Python :: 3 :: Only
Classifier: Topic :: Software Development
Classifier: Topic :: Utilities
Requires-Python: >=3.10
License-File: apache-2.0.LICENSE
License-File: NOTICE
License-File: AUTHORS.rst
License-File: CHANGELOG.rst
License-File: CODE_OF_CONDUCT.rst
License-File: README.rst
Requires-Dist: attrs!=20.1.0,>=18.1
Requires-Dist: click>7.0
Requires-Dist: colorama>=0.3.9
Requires-Dist: commoncode>=30.0.0
Requires-Dist: dparse2>=0.7.0
Requires-Dist: fasteners>=0.17.3
Requires-Dist: importlib_metadata>=4.12.0
Requires-Dist: packageurl_python>=0.9.0
Requires-Dist: pkginfo2>=30.0.0
Requires-Dist: pip-requirements-parser>=32.0.1
Requires-Dist: requests>=2.18.0
Requires-Dist: resolvelib>=1.0.0
Requires-Dist: saneyaml>=0.5.2
Requires-Dist: toml>=0.10.0
Requires-Dist: mock>=3.0.5
Requires-Dist: packvers>=21.5
Requires-Dist: aiohttp>=3.8
Requires-Dist: aiofiles>=23.1
Requires-Dist: pydantic>=2.10.0
Requires-Dist: pydantic_settings>=2.8.0
Provides-Extra: dev
Requires-Dist: pytest>=7.0.1; extra == "dev"
Requires-Dist: pytest-xdist>=2; extra == "dev"
Requires-Dist: aboutcode-toolkit>=7.0.2; extra == "dev"
Requires-Dist: twine; extra == "dev"
Requires-Dist: ruff; extra == "dev"
Requires-Dist: pytest-rerunfailures; extra == "dev"
Requires-Dist: pytest-asyncio>=0.21; extra == "dev"
Requires-Dist: Sphinx>=6.2.0; extra == "dev"
Requires-Dist: sphinx-rtd-theme>=1.0.0; extra == "dev"
Requires-Dist: sphinx-reredirects>=0.1.2; extra == "dev"
Requires-Dist: doc8>=0.11.2; extra == "dev"
Requires-Dist: sphinx-autobuild; extra == "dev"
Requires-Dist: sphinx-rtd-dark-mode>=1.3.0; extra == "dev"
Requires-Dist: sphinx-copybutton; extra == "dev"
Dynamic: license-file
